calculator/__init__.py
calculator/calculator.py
calculator_Rafiatu-0.0.1.dist-info/LICENSE
calculator_Rafiatu-0.0.1.dist-info/METADATA
calculator_Rafiatu-0.0.1.dist-info/WHEEL
calculator_Rafiatu-0.0.1.dist-info/top_level.txt
calculator_Rafiatu-0.0.1.dist-info/RECORD
