Metadata-Version: 2.1
Name: calculator-Rafiatu
Version: 0.0.1
Summary: A small calculator package
Home-page: https://github.com/Rafiatu/calculator
Author: Rafihatu Bello
Author-email: rafibella101@gmail.com
License: UNKNOWN
Project-URL: Bug Tracker, https://github.com/Rafiatu/calculator/issues
Platform: UNKNOWN
Classifier: Programming Language :: Python :: 3
Classifier: License :: OSI Approved :: MIT License
Classifier: Operating System :: OS Independent
Requires-Python: >=3.5
License-File: LICENSE
